rt_option_menu/__init__.py
rt_option_menu/frontend/.env
rt_option_menu/frontend/.prettierrc
rt_option_menu/frontend/package-lock.json
rt_option_menu/frontend/package.json
rt_option_menu/frontend/tsconfig.json
rt_option_menu/frontend/build/asset-manifest.json
rt_option_menu/frontend/build/bootstrap.min.css
rt_option_menu/frontend/build/index.html
rt_option_menu/frontend/build/precache-manifest.78afb817221145c599e92824c551ea43.js
rt_option_menu/frontend/build/service-worker.js
rt_option_menu/frontend/build/static/js/2.7b1de05b.chunk.js
rt_option_menu/frontend/build/static/js/2.7b1de05b.chunk.js.LICENSE.txt
rt_option_menu/frontend/build/static/js/2.7b1de05b.chunk.js.map
rt_option_menu/frontend/build/static/js/main.88bccac5.chunk.js
rt_option_menu/frontend/build/static/js/main.88bccac5.chunk.js.map
rt_option_menu/frontend/build/static/js/runtime-main.44d30fc2.js
rt_option_menu/frontend/build/static/js/runtime-main.44d30fc2.js.map
rt_option_menu/frontend/public/bootstrap.min.css
rt_option_menu/frontend/public/index.html
rt_option_menu/frontend/src/Icon.tsx
rt_option_menu/frontend/src/RtOptionMenu.tsx
rt_option_menu/frontend/src/index.tsx
rt_option_menu/frontend/src/react-app-env.d.ts
rt_option_menu-1.1.5.dist-info/LICENSE
rt_option_menu-1.1.5.dist-info/METADATA
rt_option_menu-1.1.5.dist-info/WHEEL
rt_option_menu-1.1.5.dist-info/top_level.txt
rt_option_menu-1.1.5.dist-info/RECORD
