Metadata-Version: 2.1
Name: rt-option-menu
Version: 1.1.5
Home-page: 
Author: Jared Foster
Author-email: jfoster@cafemedia.com
Requires-Python: >=3.6
License-File: LICENSE
Requires-Dist: streamlit (>=0.63)
